grpc_wrappers/__init__.py
grpc_wrappers/_version.py
grpc_wrappers/utils.py
grpc_wrappers/wrapper.py
grpc_wrappers/wrappers/__init__.py
grpc_wrappers/wrappers/google.py
grpc_wrappers-0.2.4.dist-info/METADATA
grpc_wrappers-0.2.4.dist-info/WHEEL
grpc_wrappers-0.2.4.dist-info/licenses/LICENSE
grpc_wrappers-0.2.4.dist-info/RECORD
